xgrads/__init__.py
xgrads/core.py
xgrads/io.py
xgrads/utils.py
xgrads-0.2.7.dist-info/licenses/LICENSE
xgrads-0.2.7.dist-info/METADATA
xgrads-0.2.7.dist-info/WHEEL
xgrads-0.2.7.dist-info/top_level.txt
xgrads-0.2.7.dist-info/RECORD
