Metadata-Version: 2.4
Name: xgrads
Version: 0.2.7
Summary: Parse and read ctl file commonly used by GrADS.
Home-page: https://github.com/miniufo/xgrads
Author: miniufo
Author-email: miniufo@163.com
License: MIT
Keywords: grads opengrads xarray dask
Classifier: Programming Language :: Python :: 3.6
Classifier: Programming Language :: Python :: 3.7
License-File: LICENSE
Requires-Dist: numpy
Requires-Dist: xarray
Requires-Dist: dask
Requires-Dist: pyproj
Dynamic: author
Dynamic: author-email
Dynamic: classifier
Dynamic: description
Dynamic: description-content-type
Dynamic: home-page
Dynamic: keywords
Dynamic: license
Dynamic: license-file
Dynamic: requires-dist
Dynamic: summary
